reponow/__init__.py
reponow/opener.py
reponow/parser.py
reponow/wcl.py
reponow-0.0.1.dist-info/METADATA
reponow-0.0.1.dist-info/WHEEL
reponow-0.0.1.dist-info/entry_points.txt
reponow-0.0.1.dist-info/licenses/LICENSE
reponow-0.0.1.dist-info/RECORD
