Metadata-Version: 2.4
Name: reponow
Version: 0.0.1
Summary: convention based repo clone, open, etc
Project-URL: Homepage, https://github.com/g0t4/course-python-functions-modules
Author-email: Wes Higbee <wes.mcclure@gmail.com>
License-Expression: MIT
License-File: LICENSE
Requires-Python: >=3.9
Requires-Dist: ipykernel>=6.29.5
Requires-Dist: ipython>=9.3.0
Requires-Dist: rich>=14.0.0
Requires-Dist: rope>=1.13.0
Requires-Dist: yapf>=0.43.0
